mwbase/__init__.py
mwbase/about.py
mwbase/attr_dict.py
mwbase/claim.py
mwbase/datavalue.py
mwbase/entity.py
mwbase/functions.py
mwbase/sitelink.py
mwbase/statement.py
mwbase/util.py
mwbase/tests/__init__.py
mwbase/tests/test_attr_dict.py
mwbase/tests/test_claim.py
mwbase/tests/test_datavalue.py
mwbase/tests/test_entity.py
mwbase/tests/test_functions.py
mwbase/tests/util.py
mwbase-0.1.5.dist-info/LICENSE
mwbase-0.1.5.dist-info/METADATA
mwbase-0.1.5.dist-info/WHEEL
mwbase-0.1.5.dist-info/top_level.txt
mwbase-0.1.5.dist-info/RECORD
