Metadata-Version: 2.1
Name: mwbase
Version: 0.1.5
Summary: Data structure normalization for MediaWiki's Wikibase
Home-page: https://github.com/mediawiki-utilities/python-mwbase
Author: Aaron Halfaker
Author-email: aaron.halfaker@gmail.com
License: MIT
Platform: UNKNOWN
